README.md
setup.cfg
setup.py
serverless_secrets/__init__.py
serverless_secrets.egg-info/PKG-INFO
serverless_secrets.egg-info/SOURCES.txt
serverless_secrets.egg-info/dependency_links.txt
serverless_secrets.egg-info/requires.txt
serverless_secrets.egg-info/top_level.txt
serverless_secrets/lib/__init__.py
serverless_secrets/lib/secrets.py
serverless_secrets/providers/__init__.py
serverless_secrets/providers/aws.py